scald/__init__.py
scald/cli.py
scald/main.py
scald/memory.py
scald/models.py
scald/agents/__init__.py
scald/agents/actor.py
scald/agents/base.py
scald/agents/context.py
scald/agents/critic.py
scald/common/__init__.py
scald/common/logger.py
scald/common/mixins.py
scald/common/workspace.py
scald/mcp/__init__.py
scald/mcp/registry.py
scald/mcp/utils.py
scald/mcp/servers/data_analysis/__init__.py
scald/mcp/servers/data_analysis/server.py
scald/mcp/servers/data_preview/__init__.py
scald/mcp/servers/data_preview/server.py
scald/mcp/servers/data_processing/__init__.py
scald/mcp/servers/data_processing/server.py
scald/mcp/servers/file_operations/__init__.py
scald/mcp/servers/file_operations/server.py
scald/mcp/servers/machine_learning/__init__.py
scald/mcp/servers/machine_learning/server.py
scald-0.1.1.dist-info/METADATA
scald-0.1.1.dist-info/WHEEL
scald-0.1.1.dist-info/entry_points.txt
scald-0.1.1.dist-info/licenses/LICENSE
scald-0.1.1.dist-info/RECORD
