Metadata-Version: 2.4
Name: scald
Version: 0.1.1
Summary: Scalable Collaborative Agents for Data Science
Author-email: Dmitry Gilemkhanov <dima.rize@yandex.ru>
License: MIT
License-File: LICENSE
Requires-Python: >=3.11
Requires-Dist: catboost>=1.2.8
Requires-Dist: chromadb>=1.3.2
Requires-Dist: docker>=7.1.0
Requires-Dist: fastmcp>=2.13.0.2
Requires-Dist: genai-prices>=0.0.35
Requires-Dist: lightgbm>=4.6.0
Requires-Dist: loguru>=0.7.3
Requires-Dist: optuna>=4.5.0
Requires-Dist: polars>=1.35.1
Requires-Dist: pydantic-ai>=1.10.0
Requires-Dist: pydantic-evals>=1.10.0
Requires-Dist: pydantic>=2.12.3
Requires-Dist: python-dotenv>=1.2.1
Requires-Dist: python-toon>=0.1.3
Requires-Dist: scikit-learn>=1.7.2
Requires-Dist: xgboost>=3.1.1
